<?xml version="1.0" encoding="UTF-8"?>
<xml>
  <file>
    <title>jpeg_write_m_byte</title>
    <breadcumbs>
      <link file="BitMiracle_LibJpeg_Classic.xml">
        <text>BitMiracle.LibJpeg.Classic namespace</text>
      </link>
      <text> :: </text>
      <link file="jpeg_compress_struct.xml">
        <text>jpeg_compress_struct</text>
      </link>
    </breadcumbs>
    <descriptionarticle only="false">
      <text>Writes a byte of special marker's data.</text> </descriptionarticle>
    <seealso>
      <ref caption="jpeg_write_m_header" file="jpeg_compress_struct.jpeg_write_m_header.xml" />
    </seealso>
    <signature>
      <function>
        <name>jpeg_write_m_byte</name>
        <return type="Void" />
        <parameters>
          <parameter name="val" type="Byte">Byte of data.</parameter>
        </parameters>
      </function>
    </signature>
  </file>
</xml>